azrail/__init__.py
azrail/azrail.py
azrail-2.7.5.dist-info/LICENSE
azrail-2.7.5.dist-info/METADATA
azrail-2.7.5.dist-info/WHEEL
azrail-2.7.5.dist-info/top_level.txt
azrail-2.7.5.dist-info/RECORD
