Metadata-Version: 2.1
Name: azrail
Version: 2.7.5
Summary: A package for generating various user agents
Home-page: https://github.com/yourusername/azrail
Author: Your Name
Author-email: your.email@example.com
License-File: LICENSE
